vcracing
