Metadata-Version: 1.0
Name: vcracing
Version: 1.0.8
Summary: Enjoy car(?) racing game. Please see https://vigne-cla.com/vc-racing/
Home-page: https://vigne-cla.com/vc-racing/
Author: Shoya Yasuda @ Viniette&Clarity
Author-email: yasuda@vigne-cla.com
License: Required: Copyright notice in any social outputs.     Permitted: Private Use, Commercial Use.     Forbidden: Sublicense, Modifications, Distribution, Patent Grant, Use Trademark, Hold Liable.
Platform: UNKNOWN
